{
  "19635a28cea4a496": {
    "processedAt": "2025-04-15T00:09:13.657Z",
    "subject": "[Binance]Payment Transaction Detail - 2025-04-14 18:49:24 (UTC)",
    "date": "2025-04-14T18:49:26.000Z",
    "transactionCount": 1,
    "transactionIds": [
      "0"
    ]
  },
  "196359e728603509": {
    "processedAt": "2025-04-15T00:09:13.657Z",
    "subject": "[Binance]Payment Transaction Detail - 2025-04-14 18:44:55 (UTC)",
    "date": "2025-04-14T18:44:56.000Z",
    "transactionCount": 1,
    "transactionIds": [
      "0"
    ]
  },
  "196359c6ee9ff2f5": {
    "processedAt": "2025-04-15T00:09:13.658Z",
    "subject": "[Binance] Login Attempted from New IP address  185.183.33.219 - 2025-04-14 18:42:44(UTC)",
    "date": "2025-04-14T18:42:45.000Z",
    "transactionCount": 0,
    "transactionIds": []
  },
  "196352a3dc289334": {
    "processedAt": "2025-04-15T00:09:13.658Z",
    "subject": "[Binance]Payment Transaction Detail - 2025-04-14 16:38:00 (UTC)",
    "date": "2025-04-14T16:38:01.000Z",
    "transactionCount": 1,
    "transactionIds": [
      "0"
    ]
  },
  "19634b655fa8e562": {
    "processedAt": "2025-04-15T00:09:13.658Z",
    "subject": "[Binance]Payment Transaction Detail - 2025-04-14 14:31:24 (UTC)",
    "date": "2025-04-14T14:31:25.000Z",
    "transactionCount": 1,
    "transactionIds": [
      "0"
    ]
  },
  "1963498de1b2dac0": {
    "processedAt": "2025-04-15T00:09:13.659Z",
    "subject": "[Binance] USDT Deposit Confirmed - 2025-04-14 13:59:13(UTC)",
    "date": "2025-04-14T13:59:14.000Z",
    "transactionCount": 1,
    "transactionIds": [
      "DEP1744675753656"
    ]
  }
}